load_env_vars_at_startup/__init__.py
load_env_vars_at_startup/__main__.py
load_env_vars_at_startup/_codemod.py
load_env_vars_at_startup/_templates.py
load_env_vars_at_startup/main.py
load_env_vars_at_startup/py.typed
load_env_vars_at_startup-0.1.0.dist-info/METADATA
load_env_vars_at_startup-0.1.0.dist-info/WHEEL
load_env_vars_at_startup-0.1.0.dist-info/entry_points.txt
load_env_vars_at_startup-0.1.0.dist-info/licenses/LICENSE
load_env_vars_at_startup-0.1.0.dist-info/RECORD
