Metadata-Version: 2.1
Name: load-env-vars-at-startup
Version: 0.1.0
Summary: Codemod to load environment variables at startup. 📝
Project-URL: Homepage, https://github.com/Kludex/load-env-vars-at-startup
Project-URL: Source, https://github.com/Kludex/load-env-vars-at-startup
Project-URL: Twitter, https://twitter.com/marcelotryle
Project-URL: Funding, https://github.com/sponsors/Kludex
Author-email: Marcelo Trylesinski <marcelotryle@email.com>
License-File: LICENSE
Classifier: Development Status :: 3 - Alpha
Classifier: Intended Audience :: Developers
Classifier: License :: OSI Approved :: MIT License
Classifier: Natural Language :: English
Classifier: Operating System :: OS Independent
Classifier: Programming Language :: Python :: 3
Classifier: Programming Language :: Python :: 3 :: Only
Classifier: Programming Language :: Python :: 3.7
Classifier: Programming Language :: Python :: 3.8
Classifier: Programming Language :: Python :: 3.9
Classifier: Programming Language :: Python :: 3.10
Classifier: Programming Language :: Python :: 3.11
Requires-Python: >=3.7
Requires-Dist: jinja2>=3.1.2<4.0.0
Requires-Dist: libcst>=0.4.7<0.5.0
Requires-Dist: typer>=0.6.1<0.7.0
